vsketch/__init__.py
vsketch/curves.py
vsketch/display.py
vsketch/easing.py
vsketch/fill.py
vsketch/shape.py
vsketch/sketch_class.py
vsketch/style.py
vsketch/utils.py
vsketch/vsketch.py
vsketch_cli/__init__.py
vsketch_cli/__main__.py
vsketch_cli/cli.py
vsketch_cli/config_widget.py
vsketch_cli/gui.py
vsketch_cli/param_widget.py
vsketch_cli/seed_widget.py
vsketch_cli/sketch_viewer.py
vsketch_cli/threads.py
vsketch_cli/utils.py
vsketch-1.2.0.dist-info/LICENSE
vsketch-1.2.0.dist-info/METADATA
vsketch-1.2.0.dist-info/WHEEL
vsketch-1.2.0.dist-info/entry_points.txt
vsketch-1.2.0.dist-info/RECORD
