Metadata-Version: 2.3
Name: vsketch
Version: 1.2.0
Summary: Plotter generative art environment
License: MIT
Author: Antoine Beyeler
Author-email: abeyeler@ab-ware.com
Requires-Python: >=3.11, <3.14
Classifier: License :: OSI Approved :: MIT License
Classifier: Programming Language :: Python :: 3
Classifier: Programming Language :: Python :: 3.11
Classifier: Programming Language :: Python :: 3.12
Classifier: Programming Language :: Python :: 3.13
Classifier: Topic :: Artistic Software
Classifier: Topic :: Multimedia :: Graphics
Requires-Dist: PySide6 (>=6.3.2)
Requires-Dist: Shapely[vectorized] (>=1.8.2)
Requires-Dist: cookiecutter (>=2.1)
Requires-Dist: matplotlib (>=3.3.3)
Requires-Dist: multiprocess (>=0.70)
Requires-Dist: numpy (>=1.20.1,<3)
Requires-Dist: pnoise (>=0.2.0)
Requires-Dist: vpype[all] (>=1.15.0)
Requires-Dist: watchfiles (>=0.12)
Project-URL: Documentation, https://vsketch.readthedocs.io/en/latest/
Project-URL: Homepage, https://github.com/abey79/vsketch
